improved_helloworld/HelloWorld.py
improved_helloworld/__init__.py
improved_helloworld-0.3.dist-info/LICENSE
improved_helloworld-0.3.dist-info/METADATA
improved_helloworld-0.3.dist-info/WHEEL
improved_helloworld-0.3.dist-info/entry_points.txt
improved_helloworld-0.3.dist-info/top_level.txt
improved_helloworld-0.3.dist-info/RECORD
