Metadata-Version: 2.1
Name: improved_helloworld
Version: 0.3
Summary: WeatherWolf is an extension on python to speed up your coding journey by skipping the first basic lesson
Home-page: https://github.com/weatherwolf/Improved-HelloWorld
Author: WeatherWolf
Author-email: golfbekkers@gmail.com
Classifier: Programming Language :: Python :: 3
Classifier: License :: OSI Approved :: MIT License
Classifier: Operating System :: OS Independent
Requires-Python: >=3.6
License-File: LICENSE
